{
    "type": "FeatureCollection",
    "crs": {
        "type": "name",
        "properties": {
            "name": "urn:ogc:def:crs:OGC:1.3:CRS84"
        }
    },
    "features": [
        {
            "type": "Feature",
            "properties": {
                "Name": "Comendador Venâncio",
                "description": null,
                "timestamp": null,
                "begin": null,
                "end": null,
                "altitudeMode": null,
                "tessellate": -1,
                "extrude": 0,
                "visibility": 0,
                "drawOrder": null,
                "icon": null
            },
            "geometry": {
                "type": "Point",
                "coordinates": [
                    -42.10417754039598,
                    -21.179235600297879,
                    0.0
                ]
            }
        },
        {
            "type": "Feature",
            "properties": {
                "Name": "Retiro do Muriaé",
                "description": null,
                "timestamp": null,
                "begin": null,
                "end": null,
                "altitudeMode": null,
                "tessellate": -1,
                "extrude": 0,
                "visibility": 0,
                "drawOrder": null,
                "icon": null
            },
            "geometry": {
                "type": "Point",
                "coordinates": [
                    -42.013891889900698,
                    -21.177792607074419,
                    0.0
                ]
            }
        }
    ]
}